[
  {
    "index": 113,
    "firebaseId": "3769c165-c384-4235-9fad-1e06d7cad92b",
    "name": "EURUSD",
    "date": "2025-06-04T16:26:37.000Z",
    "amount": -489,
    "type": "loss",
    "shareId": "share_3769c165-c384-4235-9fad-1e06d7cad92b_1749986780700_ryv8tihn7",
    "tags": [
      "Strategies:Daily Volume Setup",
      "Confluence:3x Displacement",
      "Confluence:Liquidity Sweep"
    ]
  },
  {
    "index": 119,
    "firebaseId": "32f88082-8dea-495f-9d6c-4ad11ab636bf",
    "name": "EURUSD",
    "date": "2025-06-02T17:49:17.000Z",
    "amount": 733,
    "type": "win",
    "shareId": "share_32f88082-8dea-495f-9d6c-4ad11ab636bf_1749989643711_o3khs2k54",
    "tags": [
      "Strategies:Daily Volume Setup",
      "Confluence:3x Displacement",
      "Confluence:5min IFVG"
    ]
  },
  {
    "index": 139,
    "firebaseId": "3d7f2a1b-4cc8-4b32-96be-e8e10a6ef513",
    "name": "EURUSD",
    "date": "2025-06-11T23:13:41.000Z",
    "amount": 726,
    "type": "win",
    "shareId": "share_3d7f2a1b-4cc8-4b32-96be-e8e10a6ef513_1750076661463_ygk7zspb6",
    "tags": [
      "Strategies:Daily Volume Setup",
      "Confluence:3x Displacement",
      "Counter Trend:No"
    ]
  }
]